UpStorageApiClient/VERSION
UpStorageApiClient/__init__.py
UpStorageApiClient/api.py
UpStorageApiClient/version.py
UpStorageApiClient-1.1.dist-info/LICENSE.md
UpStorageApiClient-1.1.dist-info/METADATA
UpStorageApiClient-1.1.dist-info/WHEEL
UpStorageApiClient-1.1.dist-info/top_level.txt
UpStorageApiClient-1.1.dist-info/RECORD
