Metadata-Version: 2.1
Name: UpStorageApiClient
Version: 1.1
Summary: UpStorage Api Client.
Home-page: https://github.com/QuackCoding/UpStorageApiClient
Author: Sakib (Florian Dedov)
Author-email: <mail@neuralnine.com>
License: UNKNOWN
Keywords: python,storage,api,upstorage,UpStorageApiClient
Platform: UNKNOWN
Classifier: Development Status :: 5 - Production/Stable
Classifier: Intended Audience :: Developers
Classifier: Programming Language :: Python :: 3
Classifier: Operating System :: Unix
Classifier: Operating System :: MacOS :: MacOS X
Classifier: Operating System :: Microsoft :: Windows
Requires-Dist: requests
